snc/__init__.py
snc/snc.py
snc/helpers/__init__.py
snc/helpers/distance_matrix.py
snc/helpers/hparam_functions.py
snc/helpers/snn_knn.py
snc/helpers/visualization.py
snc-0.2.1.dist-info/LICENSE
snc-0.2.1.dist-info/METADATA
snc-0.2.1.dist-info/WHEEL
snc-0.2.1.dist-info/top_level.txt
snc-0.2.1.dist-info/RECORD
