Metadata-Version: 2.1
Name: snc
Version: 0.2.1
Summary: Implementation of Steadiness & Cohesiveness
Home-page: https://github.com/hj-n/steadiness-cohesiveness
Author: Hyeon Jeon
Author-email: hj@hcil.snu.ac.kr
License: UNKNOWN
Platform: UNKNOWN
Classifier: Programming Language :: Python :: 3
Classifier: License :: OSI Approved :: MIT License
Classifier: Operating System :: OS Independent
Requires-Python: >=3.8.5
